{
  "alerts": {
    "MEL:perf:10229203824839": {
      "firstSeen": "2026-07-12T16:08:53.131Z",
      "lastAlerted": "2026-07-14T17:01:09.718Z",
      "lastSeen": "2026-07-14T22:47:05.957Z",
      "match": "Suite Essentials: England vs Argentina (Semi-final, US)",
      "stores": [
        "us"
      ]
    },
    "MEL:perf:10229203824840": {
      "firstSeen": "2026-07-14T21:51:05.961Z",
      "lastAlerted": "2026-07-14T21:51:05.961Z",
      "lastSeen": "2026-07-14T22:47:05.957Z",
      "match": "Suite Essentials: France vs FIXTURE (Third-place Final, US)",
      "stores": [
        "us"
      ]
    }
  }
}
