{
  "alerts": {
    "MEL:perf:10229203824846": {
      "firstSeen": "2026-07-03T03:05:27.867Z",
      "lastAlerted": "2026-07-03T03:05:27.867Z",
      "lastSeen": "2026-07-03T04:40:27.169Z",
      "match": "Suite Essentials: Australia vs Egypt (Round of 32, US)",
      "stores": [
        "us"
      ]
    },
    "MEL:perf:10229203824831": {
      "firstSeen": "2026-07-03T03:05:27.867Z",
      "lastAlerted": "2026-07-03T03:05:27.867Z",
      "lastSeen": "2026-07-03T04:30:27.382Z",
      "match": "Suite Essentials: W83 vs Spain (Round of 16, US)",
      "stores": [
        "us"
      ]
    },
    "MEL:perf:10229203824845": {
      "firstSeen": "2026-07-03T04:10:25.947Z",
      "lastAlerted": "2026-07-03T04:10:25.947Z",
      "lastSeen": "2026-07-03T04:35:25.795Z",
      "match": "Suite Essentials: Colombia vs Ghana (Round of 32, US)",
      "stores": [
        "us"
      ]
    }
  }
}
