{
  "alerts": {
    "MEL:perf:10229203824846": {
      "firstSeen": "2026-06-30T03:00:25.729Z",
      "lastAlerted": "2026-07-02T09:20:29.485Z",
      "lastSeen": "2026-07-02T10:45:26.273Z",
      "match": "Suite Essentials: Australia vs Egypt (Round of 32, US)",
      "stores": [
        "us"
      ]
    },
    "MEL:perf:10229203824829": {
      "firstSeen": "2026-07-01T18:40:28.086Z",
      "lastAlerted": "2026-07-02T06:45:35.236Z",
      "lastSeen": "2026-07-02T10:45:26.273Z",
      "match": "Suite Essentials: Canada vs Morocco (Round of 16, US)",
      "stores": [
        "us"
      ]
    },
    "MEL:perf:10229203824845": {
      "firstSeen": "2026-07-01T23:45:27.057Z",
      "lastAlerted": "2026-07-02T05:55:29.032Z",
      "lastSeen": "2026-07-02T10:15:28.097Z",
      "match": "Suite Essentials: Colombia vs Ghana (Round of 32, US)",
      "stores": [
        "us"
      ]
    }
  }
}
